shapr/__init__.py
shapr/_settings.py
shapr/analyse_interpolation.py
shapr/analyse_topology.py
shapr/analyse_wandb.py
shapr/calculate_persistence_diagrams.py
shapr/data_generator.py
shapr/evaluate.py
shapr/evaluation.py
shapr/main.py
shapr/make_gallery.py
shapr/metrics.py
shapr/model.py
shapr/run.py
shapr/run_train_script.py
shapr/utils.py
shapr/viewer.py
shapr_torch-0.0.1.dist-info/METADATA
shapr_torch-0.0.1.dist-info/WHEEL
shapr_torch-0.0.1.dist-info/top_level.txt
shapr_torch-0.0.1.dist-info/RECORD
