Metadata-Version: 2.1
Name: shapr-torch
Version: 0.0.1
Summary: UNKNOWN
Home-page: https://github.com/marrlab/SHAPR_torch/
Author: Dominik Waibel, Bastian Rieck
Author-email: dominik.waibel@helmholtz-muenchen.de
License: MIT
Keywords: Computational Biology Deep Learning
Platform: UNKNOWN
Classifier: Development Status :: 3 - Alpha
Classifier: Topic :: Scientific/Engineering :: Image Recognition
Classifier: License :: OSI Approved :: MIT License
Requires-Dist: torch
Requires-Dist: imageio
Requires-Dist: scikit-image
Requires-Dist: scikit-learn
